scrapy_requests/__init__.py
scrapy_requests/middleware.py
scrapy_requests/request.py
tests/__init__.py
tests/test_request.py
scrapy_requests-0.2.0.dist-info/LICENSE
scrapy_requests-0.2.0.dist-info/METADATA
scrapy_requests-0.2.0.dist-info/WHEEL
scrapy_requests-0.2.0.dist-info/top_level.txt
scrapy_requests-0.2.0.dist-info/RECORD
