Metadata-Version: 2.1
Name: scrapy-requests
Version: 0.2.0
Summary: Scrapy with requests-html
Home-page: https://github.com/rafyzg/scrapy-requests
Author: Refael Yzg
Author-email: rafi.yzgeav@gmail.com
License: UNKNOWN
Platform: UNKNOWN
Classifier: Programming Language :: Python :: 3
Classifier: License :: OSI Approved :: MIT License
Classifier: Intended Audience :: Developers
Classifier: Operating System :: OS Independent
Classifier: Programming Language :: Python :: 3.6
Classifier: Programming Language :: Python :: 3.7
Classifier: Programming Language :: Python :: 3.8
Classifier: Programming Language :: Python :: 3.9
Requires-Python: >=3.6
Requires-Dist: scrapy (>=2.0.0)
Requires-Dist: requests-html (>=0.10.0)
